{
    "DNDConfig": null,
    "__parentReadjusting__": false,
    "_height_": {
        "type": "ref",
        "value": "preferred"
    },
    "_margin_": [
        1,
        1,
        1,
        1
    ],
    "_padding_": [
        0,
        0,
        0,
        0
    ],
    "_right_": {
        "type": "string",
        "value": "15%"
    },
    "_skin_": "sb0d33fe1bdb400eb4f783ba67e530d9",
    "_text_": "11:48 AM",
    "_top_": {
        "type": "string",
        "value": "25%"
    },
    "_width_": {
        "type": "ref",
        "value": "preferred"
    },
    "_wrapping_": 2,
    "canUpdateUI": true,
    "channel": "mobile",
    "containerId": true,
    "containerWeight": 100,
    "containerweight": 100,
    "contentAlignment": 4,
    "contentalignment": 4,
    "enabled": false,
    "height": {
        "type": "ref",
        "value": "preferred"
    },
    "id": "lblTime",
    "info": null,
    "ipad": {
        "psp": {
            "wrapping": 2
        }
    },
    "iphone": {
        "@class": "com.kony.gen.viz.model.component.property.label.IPhoneLabelProperty",
        "psp": {
            "wrapping": 2
        }
    },
    "isSegmentChild": false,
    "isVisible": true,
    "isvisible": true,
    "kuid": "b1fab861b97d4ec9b73a8a356001fddc",
    "margin": [
        1,
        1,
        1,
        1
    ],
    "name": "kony.ui.Label",
    "padding": [
        0,
        0,
        0,
        0
    ],
    "parent": "flexMessage",
    "pf": "messageTemp",
    "render": true,
    "right": "15%",
    "skin": "sb0d33fe1bdb400eb4f783ba67e530d9",
    "text": "11:48 AM",
    "toolTip": "",
    "tooltip": "",
    "top": "25%",
    "wType": "Label",
    "widgetAlignment": 5,
    "width": {
        "type": "ref",
        "value": "preferred"
    },
    "wrapping": 2,
    "zIndex": 2,
    "zindex": 2
}