{
    "DNDConfig": null,
    "__parentReadjusting__": false,
    "_bottom_": {
        "type": "number",
        "value": "0"
    },
    "_height_": {
        "type": "string",
        "value": "80dp"
    },
    "_left_": {
        "type": "string",
        "value": "0dp"
    },
    "_margin_": [
        0,
        0,
        0,
        0
    ],
    "_padding_": [
        0,
        0,
        0,
        0
    ],
    "_skin_": "s7a4c9416c2b4938a145d640e2b4856f",
    "_width_": {
        "type": "string",
        "value": "100%"
    },
    "allboxes": [],
    "autogrowMode": 0,
    "autogrowmode": 0,
    "bottom": 0,
    "canUpdateUI": true,
    "children": [
        "btnLegal",
        "Label0d6d5baad497f4f"
    ],
    "clipBounds": true,
    "clipbounds": true,
    "containerWeight": 100,
    "containerweight": 100,
    "enableScrolling": true,
    "enabled": false,
    "enablescrolling": true,
    "height": "80dp",
    "id": "flexLegal",
    "info": null,
    "isVisible": true,
    "isvisible": true,
    "kuid": "7cee2db1e7d2454cab7ad4b85a83fb7d",
    "layoutType": 2,
    "layouttype": 2,
    "left": "0dp",
    "margin": [
        0,
        0,
        0,
        0
    ],
    "name": "kony.ui.FlexContainer",
    "orientation": 6,
    "padding": [
        0,
        0,
        0,
        0
    ],
    "parent": "flexMenu",
    "percent": true,
    "pf": "frm004Home",
    "render": true,
    "skin": "s7a4c9416c2b4938a145d640e2b4856f",
    "snapGridSize": 10,
    "snapToGrid": true,
    "snapgridsize": 10,
    "snaptogrid": true,
    "wType": "FlexContainer",
    "widgetAlignment": 1,
    "widgetalignment": 1,
    "width": "100%",
    "zIndex": 69,
    "zindex": 69
}