{
    "@class": "com.kony.gen.viz.model.component.KVizLabel",
    "DNDConfig": null,
    "__parentReadjusting__": false,
    "_height_": {
        "type": "ref",
        "value": "preferred"
    },
    "_margin_": [
        1,
        1,
        1,
        1
    ],
    "_padding_": [
        0,
        0,
        0,
        0
    ],
    "_skin_": "sc223565e9834200b398c685e8bbf846",
    "_text_": "R250 - R275",
    "_top_": {
        "type": "string",
        "value": "360dp"
    },
    "_width_": {
        "type": "ref",
        "value": "preferred"
    },
    "_wrapping_": 2,
    "canUpdateUI": true,
    "centerX": "50%",
    "centerx": {
        "type": "string",
        "value": "50%"
    },
    "containerWeight": 100,
    "containerweight": 100,
    "contentAlignment": 4,
    "contentalignment": 4,
    "enabled": false,
    "height": {
        "type": "ref",
        "value": "preferred"
    },
    "id": "lblTripPrice",
    "info": null,
    "ipad": {
        "psp": {
            "wrapping": 2
        }
    },
    "iphone": {
        "psp": {
            "wrapping": 2
        }
    },
    "isVisible": true,
    "isvisible": true,
    "kuid": "1eae72a68d8d448aa3cca77728c812dd",
    "margin": [
        1,
        1,
        1,
        1
    ],
    "name": "kony.ui.Label",
    "padding": [
        0,
        0,
        0,
        0
    ],
    "parent": "flexScrollFlagDown",
    "pf": "frmFlagDown",
    "render": true,
    "skin": "sc223565e9834200b398c685e8bbf846",
    "text": "R250 - R275",
    "toolTip": "",
    "tooltip": "",
    "top": "360dp",
    "wType": "Label",
    "widgetAlignment": 5,
    "width": {
        "type": "ref",
        "value": "preferred"
    },
    "wrapping": 2,
    "zIndex": 2,
    "zindex": 2
}