{
    "DNDConfig": null,
    "__parentReadjusting__": false,
    "_height_": {
        "type": "string",
        "value": "50dp"
    },
    "_left_": {
        "type": "string",
        "value": "0%"
    },
    "_margin_": [
        0,
        0,
        0,
        0
    ],
    "_padding_": [
        0,
        0,
        0,
        0
    ],
    "_placeholder_": "",
    "_skin_": "s026360184534280819e362c5b80ece1",
    "_text_": "Your Email Address",
    "_top_": {
        "type": "string",
        "value": "50dp"
    },
    "_width_": {
        "type": "string",
        "value": "100%"
    },
    "autoCapitalize": "none",
    "autoComplete": false,
    "autoCorrect": false,
    "autoFilter": false,
    "autocapitalize": "none",
    "autocomplete": false,
    "autocorrect": false,
    "autofilter": false,
    "canUpdateUI": true,
    "channel": "mobile",
    "containerHeight": "",
    "containerHeightMode": 1,
    "containerWeight": 100,
    "containerheight": "",
    "containerheightmode": 1,
    "containerweight": 100,
    "contentAlignment": 5,
    "contentalignment": 5,
    "enabled": false,
    "focusSkin": "se9597eb8463440ba121ef7aad9616c9",
    "focusskin": "se9597eb8463440ba121ef7aad9616c9",
    "height": "50dp",
    "id": "txfEmail",
    "info": null,
    "isVisible": true,
    "isvisible": true,
    "keyboardtype": "A",
    "kuid": "e4b0718076b14f0f9c5d18b495af99c8",
    "left": "0%",
    "margin": [
        0,
        0,
        0,
        0
    ],
    "mode": "A",
    "name": "kony.ui.TextBox2",
    "padding": [
        0,
        0,
        0,
        0
    ],
    "parent": "scrollSignupBottom",
    "pf": "frm002SignupScreen",
    "placeholder": "",
    "placeholderSkin": "s242100737cf47ed8fd91bbb5af00c53",
    "placeholderskin": "s242100737cf47ed8fd91bbb5af00c53",
    "render": true,
    "secureTextEntry": false,
    "securetextentry": false,
    "skin": "s026360184534280819e362c5b80ece1",
    "text": "Your Email Address",
    "textInputMode": "A",
    "textinputmode": "A",
    "toolTip": "",
    "top": "50dp",
    "viewType": "default",
    "viewtype": "default",
    "wType": "TextField",
    "widgetAlignment": 5,
    "width": "100%"
}